varvamp/__init__.py
varvamp/__main__.py
varvamp/command.py
varvamp/scripts/__init__.py
varvamp/scripts/alignment.py
varvamp/scripts/blast.py
varvamp/scripts/consensus.py
varvamp/scripts/default_config.py
varvamp/scripts/get_config.py
varvamp/scripts/logging.py
varvamp/scripts/param_estimation.py
varvamp/scripts/primers.py
varvamp/scripts/qpcr.py
varvamp/scripts/regions.py
varvamp/scripts/reporting.py
varvamp/scripts/scheme.py
varvamp-1.2.2.dist-info/METADATA
varvamp-1.2.2.dist-info/WHEEL
varvamp-1.2.2.dist-info/entry_points.txt
varvamp-1.2.2.dist-info/top_level.txt
varvamp-1.2.2.dist-info/RECORD
