Metadata-Version: 2.2
Name: varvamp
Version: 1.2.2
Summary: Variable VirusAMPlicons (varVAMP) is a tool to design primers for highly diverse viruses
Home-page: https://github.com/jonas-fuchs/varVAMP
Author: Dr. Jonas Fuchs
Author-email: jonas.fuchs@uniklinik-freiburg.de
Classifier: Programming Language :: Python :: 3.9
Classifier: License :: OSI Approved :: GNU General Public License v3 or later (GPLv3+)
Requires-Python: >=3.9
Requires-Dist: biopython>=1.79
Requires-Dist: matplotlib>=3.5.1
Requires-Dist: primer3-py>=1.1.0
Requires-Dist: pandas>=1.4.4
Requires-Dist: numpy>=1.23.3
Requires-Dist: seqfold>=0.7.15
Dynamic: author
Dynamic: author-email
Dynamic: classifier
Dynamic: description
Dynamic: description-content-type
Dynamic: home-page
Dynamic: requires-dist
Dynamic: requires-python
Dynamic: summary
